[
  {
    "Device Id": "9f33a75302554dd2",
    "username": "ADMINSS",
    "password": "1234",
    "expiry": "2029-10-15",
    "paymentUSD": 0,
    "paymentBDT": 0,
    "allowoffline": false
  },
  {
    "Device Id": "b18e006865f4fd40",
    "username": "Daney1234",
    "password": "Daney@1",
    "expiry": "2026-09-29",
    "paymentUSD": 45,
    "paymentBDT": 0,
    "allowoffline": false
  },
  {
    "Device Id": "4738e444c4db0e",
    "username": "andresvxt",
    "password": "andrevxt1234",
    "expiry": "2027-01-24",
    "paymentUSD": 0,
    "paymentBDT": 0,
    "allowoffline": false
  },
  {
    "username": "Razorkid8",
    "Device Id": "b73073cf60de8dfe",
    "password": "Razorkid@88",
    "expiry": "2027-02-02",
    "paymentUSD": 30,
    "paymentBDT": 0,
    "allowoffline": false,
    "blocked": false
  },
  {
    "username": "Na12",
    "Device Id": "eb930cfa2a672fa",
    "password": "Na@2",
    "expiry": "2027-02-02",
    "paymentUSD": 0,
    "paymentBDT": 200,
    "allowoffline": false,
    "blocked": false
  },
  {
    "username": "AL12",
    "Device Id": "9a14064d070990",
    "password": "12345",
    "expiry": "2027-03-02",
    "paymentUSD": 6,
    "paymentBDT": 0,
    "allowoffline": false,
    "blocked": false
  },
  {
    "username": "A0987",
    "Device Id": "10ce56c0f64965fc",
    "password": "B0987",
    "expiry": "2027-02-04",
    "paymentUSD": 6,
    "paymentBDT": 0,
    "allowoffline": false,
    "blocked": false
  },
  {
    "username": "creed",
    "Device Id": "cf111eb1d4588b7f",
    "password": "creed@1",
    "expiry": "2027-02-05",
    "paymentUSD": 20,
    "paymentBDT": 0,
    "allowoffline": false,
    "blocked": false
  },
  {
    "username": "Adminn",
    "Device Id": "78313c79c5ad0d14",
    "password": "123",
    "expiry": "2040-02-02",
    "paymentUSD": 0,
    "paymentBDT": 0,
    "allowoffline": false,
    "blocked": false
  },
  {
    "username": "Nadhir",
    "Device Id": "13d2aceebbe2b",
    "password": "B1234",
    "expiry": "2027-02-02",
    "paymentUSD": 13,
    "paymentBDT": 0,
    "allowoffline": false,
    "blocked": false
  },
  {
    "username": "A2",
    "Device Id": "a78a8f5980d643",
    "password": "A11",
    "expiry": "2027-02-02",
    "paymentUSD": 0,
    "paymentBDT": 0,
    "allowoffline": false,
    "blocked": false
  }
]